oplangchain/__init__.py
oplangchain/agents/__init__.py
oplangchain/agents/agent.py
oplangchain/agents/agent_iterator.py
oplangchain/agents/agent_toolkits/__init__.py
oplangchain/agents/agent_toolkits/amadeus/toolkit.py
oplangchain/agents/agent_toolkits/azure_cognitive_services.py
oplangchain/agents/agent_toolkits/base.py
oplangchain/agents/agent_toolkits/conversational_retrieval/__init__.py
oplangchain/agents/agent_toolkits/conversational_retrieval/openai_functions.py
oplangchain/agents/agent_toolkits/conversational_retrieval/tool.py
oplangchain/agents/agent_toolkits/csv/__init__.py
oplangchain/agents/agent_toolkits/csv/base.py
oplangchain/agents/agent_toolkits/file_management/__init__.py
oplangchain/agents/agent_toolkits/file_management/toolkit.py
oplangchain/agents/agent_toolkits/github/__init__.py
oplangchain/agents/agent_toolkits/github/toolkit.py
oplangchain/agents/agent_toolkits/gmail/__init__.py
oplangchain/agents/agent_toolkits/gmail/toolkit.py
oplangchain/agents/agent_toolkits/jira/__init__.py
oplangchain/agents/agent_toolkits/jira/toolkit.py
oplangchain/agents/agent_toolkits/json/__init__.py
oplangchain/agents/agent_toolkits/json/base.py
oplangchain/agents/agent_toolkits/json/prompt.py
oplangchain/agents/agent_toolkits/json/toolkit.py
oplangchain/agents/agent_toolkits/multion/__init__.py
oplangchain/agents/agent_toolkits/multion/toolkit.py
oplangchain/agents/agent_toolkits/nla/__init__.py
oplangchain/agents/agent_toolkits/nla/tool.py
oplangchain/agents/agent_toolkits/nla/toolkit.py
oplangchain/agents/agent_toolkits/office365/__init__.py
oplangchain/agents/agent_toolkits/office365/toolkit.py
oplangchain/agents/agent_toolkits/openapi/__init__.py
oplangchain/agents/agent_toolkits/openapi/base.py
oplangchain/agents/agent_toolkits/openapi/planner.py
oplangchain/agents/agent_toolkits/openapi/planner_prompt.py
oplangchain/agents/agent_toolkits/openapi/prompt.py
oplangchain/agents/agent_toolkits/openapi/spec.py
oplangchain/agents/agent_toolkits/openapi/toolkit.py
oplangchain-0.1.6.dist-info/entry_points.txt
oplangchain-0.1.6.dist-info/METADATA
oplangchain-0.1.6.dist-info/WHEEL
oplangchain-0.1.6.dist-info/RECORD
